{
  "patterns": [
    {
      "exterior": {
        "emissive": false,
        "texture": "black_archive:textures/blockentity/shell/pillar/pillar_shell.png"
      },
      "id": "black_archive:default",
      "interior": {
        "emissive": false,
        "texture": "black_archive:textures/blockentity/shell/pillar/pillar_door.png"
      },
      "name_component": "{\"color\":\"yellow\",\"text\":\"Default\"}",
      "sound_profile": {
        "sounds": {
          "tardis_refined:door_close": {
            "pitch": 1.0,
            "sound_event": {
              "sound_id": "minecraft:block.wooden_door.close"
            },
            "volume": 1.4
          },
          "tardis_refined:door_lock": {
            "pitch": 1.0,
            "sound_event": {
              "sound_id": "minecraft:block.wooden_trapdoor.close"
            },
            "volume": 1.4
          },
          "tardis_refined:door_open": {
            "pitch": 1.0,
            "sound_event": {
              "sound_id": "minecraft:block.wooden_door.open"
            },
            "volume": 1.0
          },
          "tardis_refined:door_unlock": {
            "pitch": 1.0,
            "sound_event": {
              "sound_id": "minecraft:block.wooden_trapdoor.open"
            },
            "volume": 1.0
          }
        }
      }
    }
  ]
}